odoo8_addon_field_char_transformed-8.0.1.0.0-py2.7-nspkg.pth
odoo_addons/field_char_transformed/field_char_stripped.py
odoo_addons/field_char_transformed/__openerp__.py
odoo_addons/field_char_transformed/__init__.py
odoo_addons/field_char_transformed/README.rst
odoo_addons/field_char_transformed/field_char_transformed.py
odoo_addons/field_char_transformed/tests/test_field_char_transformed.py
odoo_addons/field_char_transformed/tests/__init__.py
odoo_addons/field_char_transformed/static/description/icon.png
odoo8_addon_field_char_transformed-8.0.1.0.0.dist-info/top_level.txt
odoo8_addon_field_char_transformed-8.0.1.0.0.dist-info/WHEEL
odoo8_addon_field_char_transformed-8.0.1.0.0.dist-info/RECORD
odoo8_addon_field_char_transformed-8.0.1.0.0.dist-info/metadata.json
odoo8_addon_field_char_transformed-8.0.1.0.0.dist-info/DESCRIPTION.rst
odoo8_addon_field_char_transformed-8.0.1.0.0.dist-info/METADATA
odoo8_addon_field_char_transformed-8.0.1.0.0.dist-info/namespace_packages.txt
